cal_publish_python/__init__.py
cal_publish_python/__main__.py
cal_publish_python/argbuilder.py
cal_publish_python/cli.py
cal_publish_python/config.py
cal_publish_python/publish_docs.py
cal_publish_python/publish_pypi.py
cal_publish_python/version.py
cal_publish_python-0.1.0.dist-info/METADATA
cal_publish_python-0.1.0.dist-info/WHEEL
cal_publish_python-0.1.0.dist-info/entry_points.txt
cal_publish_python-0.1.0.dist-info/licenses/LICENSE
cal_publish_python-0.1.0.dist-info/RECORD
