Metadata-Version: 2.4
Name: cal-publish-python
Version: 0.1.0
Summary: CLI tool to publish Python packages and documentation with external configuration
Project-URL: Repository, https://gitlab.com/cyberassessmentlabs/public/tools/cal-publish-python
Project-URL: Documentation, https://cyberassessmentlabs.gitlab.io/public/docs/cal-publish-python/latest
Author: Cyber Assessment Labs
License-Expression: MIT
License-File: LICENSE
Classifier: Development Status :: 4 - Beta
Classifier: Environment :: Console
Classifier: Intended Audience :: Developers
Classifier: License :: OSI Approved :: MIT License
Classifier: Operating System :: OS Independent
Classifier: Programming Language :: Python :: 3
Classifier: Programming Language :: Python :: 3.14
Classifier: Topic :: Software Development :: Libraries :: Python Modules
Requires-Python: >=3.14
Requires-Dist: gitlab-pages-upload
Requires-Dist: twine>=6.0.0
